setup.cfg
setup.py
cric_score/__init__.py
cric_score/main.py
cric_score.egg-info/PKG-INFO
cric_score.egg-info/SOURCES.txt
cric_score.egg-info/dependency_links.txt
cric_score.egg-info/entry_points.txt
cric_score.egg-info/top_level.txt