Metadata-Version: 1.0
Name: cric-score
Version: 0.1.1
Summary: Get Live Cricket Scores in Command Line
Home-page: https://github.com/sourav0007/cric_score
Author: Sourav Verma
Author-email: souravverma095@gmail.com
License: MIT
Keywords: Live Cricket scores from espncricinfo.
Platform: UNKNOWN
